MANIFEST.in
README.md
setup.py
examples/test.py
examples/test.qss
pyqss/__init__.py
pyqss.egg-info/PKG-INFO
pyqss.egg-info/SOURCES.txt
pyqss.egg-info/dependency_links.txt
pyqss.egg-info/not-zip-safe
pyqss.egg-info/requires.txt
pyqss.egg-info/top_level.txt
pyqss/i18n/__init__.py
pyqss/i18n/en.json
pyqss/i18n/zh.json
pyqss/sci/__init__.py
pyqss/sci/commenter.py
pyqss/sci/editor.py
pyqss/sci/keywords.py
pyqss/sci/lexer.py
pyqss/theme/__init__.py
pyqss/theme/default.qss
pyqss/ui/find_replace.py
pyqss/ui/images_rc.py
pyqss/ui/main.py
pyqss/widgets/__init__.py
pyqss/widgets/find_replace.py
pyqss/widgets/frameless_window.py
pyqss/widgets/main.py