Metadata-Version: 2.1
Name: pyqss
Version: 1.4.0
Summary: QSS Editor
Home-page: https://github.com/luolingchun/pyqss
Author: llc
Author-email: luolingchun.com@gmail.com
License: GPLv3
Platform: any
Requires-Python: >=3.6
